zage/__init__.py
zage/payments.py
zage-0.3.2.dist-info/LICENSE
zage-0.3.2.dist-info/METADATA
zage-0.3.2.dist-info/WHEEL
zage-0.3.2.dist-info/top_level.txt
zage-0.3.2.dist-info/RECORD
