Metadata-Version: 2.1
Name: zage
Version: 0.3.2
Summary: Python bindings for the Zage API
Home-page: https://pypi.org/project/zage/
Author: Zage Inc.
Author-email: support@zage.app
License: MIT
Keywords: zage api payments
Classifier: Development Status :: 4 - Beta
Classifier: Intended Audience :: Developers
Classifier: License :: OSI Approved :: MIT License
Classifier: Operating System :: OS Independent
Classifier: Programming Language :: Python
Classifier: Programming Language :: Python :: 3
Classifier: Programming Language :: Python :: 3.4
Classifier: Programming Language :: Python :: 3.5
Classifier: Programming Language :: Python :: 3.6
Classifier: Programming Language :: Python :: 3.7
Classifier: Programming Language :: Python :: 3.8
Classifier: Programming Language :: Python :: 3.9
Classifier: Programming Language :: Python :: Implementation :: PyPy
Classifier: Topic :: Software Development :: Libraries :: Python Modules
Requires-Python: >=2.7, !=3.0.*, !=3.1.*, !=3.2.*, !=3.3.*
License-File: LICENSE
Requires-Dist: requests[security] (>=2.20) ; python_version < "3.0"
Requires-Dist: requests (>=2.20) ; python_version >= "3.0"
